{
  "project_info": {
    "project_number": "165379384819",
    "project_id": "lovi-fdfca",
    "storage_bucket": "lovi-fdfca.appspot.com"
  },
  "client": [
    {
      "client_info": {
        "mobilesdk_app_id": "1:165379384819:android:66c33daff1325f9af7de86",
        "android_client_info": {
          "package_name": "com.lovi"
        }
      },
      "oauth_client": [
        {
          "client_id": "165379384819-skeuibhbh088f2gcagej39ka7b1803t1.apps.googleusercontent.com",
          "client_type": 1,
          "android_info": {
            "package_name": "com.lovi",
            "certificate_hash": "6ef398993fae6ff7519f73ad96131d2b43e4bc77"
          }
        },
        {
          "client_id": "165379384819-3qcsu9pdkk4th7rvf1of34fnl9mbdo27.apps.googleusercontent.com",
          "client_type": 3
        }
      ],
      "api_key": [
        {
          "current_key": "AIzaSyDXY6xGINzKnqmGuPugCWhEk_9-39t3fTA"
        }
      ],
      "services": {
        "appinvite_service": {
          "other_platform_oauth_client": [
            {
              "client_id": "165379384819-3qcsu9pdkk4th7rvf1of34fnl9mbdo27.apps.googleusercontent.com",
              "client_type": 3
            }
          ]
        }
      }
    }
  ],
  "configuration_version": "1"
}